scrutiny/__init__.py
scrutiny/__main__.py
scrutiny/exceptions.py
scrutiny/py.typed
scrutiny/cli/__init__.py
scrutiny/cli/cli.py
scrutiny/cli/commands/__init__.py
scrutiny/cli/commands/add_alias.py
scrutiny/cli/commands/base_command.py
scrutiny/cli/commands/datalog_info.py
scrutiny/cli/commands/delete_datalog.py
scrutiny/cli/commands/elf2varmap.py
scrutiny/cli/commands/export_datalog.py
scrutiny/cli/commands/get_firmware_id.py
scrutiny/cli/commands/gui.py
scrutiny/cli/commands/install_sfd.py
scrutiny/cli/commands/list_datalog.py
scrutiny/cli/commands/list_sfd.py
scrutiny/cli/commands/make_metadata.py
scrutiny/cli/commands/make_sfd.py
scrutiny/cli/commands/noop.py
scrutiny/cli/commands/runtest.py
scrutiny/cli/commands/server.py
scrutiny/cli/commands/tag_firmware_id.py
scrutiny/cli/commands/uninstall_sfd.py
scrutiny/cli/commands/version.py
scrutiny/core/__init__.py
scrutiny/core/alias.py
scrutiny/core/array.py
scrutiny/core/basic_types.py
scrutiny/core/codecs.py
scrutiny/core/datalogging.py
scrutiny/core/demo_device_sfd.py
scrutiny/core/embedded_enum.py
scrutiny/core/firmware_description.py
scrutiny/core/firmware_id.py
scrutiny/core/firmware_parser.py
scrutiny/core/logging.py
scrutiny/core/math_expr.py
scrutiny/core/memory_content.py
scrutiny/core/path_tools.py
scrutiny/core/scrutiny_path.py
scrutiny/core/sfd_storage_manager.py
scrutiny/core/struct.py
scrutiny/core/typehints.py
scrutiny/core/variable.py
scrutiny/core/variable_factory.py
scrutiny/core/varmap.py
scrutiny/core/bintools/__init__.py
scrutiny/core/bintools/demangler.py
scrutiny/core/bintools/elf_dwarf_var_extractor.py
scrutiny/core/bintools/get_var_memrange.py
scrutiny/gui/__init__.py
scrutiny/gui/app_settings.py
scrutiny/gui/component_app_interface.py
scrutiny/gui/globals.py
scrutiny/gui/gui.py
scrutiny/gui/main_window.py
scrutiny/gui/assets/__init__.py
scrutiny/gui/assets/logo-text-2-lines.png
scrutiny/gui/assets/icons/dark/alias_16x16.png
scrutiny/gui/assets/icons/dark/alias_256x256.png
scrutinydebugger-0.9.2.dist-info/licenses/LICENSE
scrutinydebugger-0.9.2.dist-info/METADATA
scrutinydebugger-0.9.2.dist-info/WHEEL
scrutinydebugger-0.9.2.dist-info/entry_points.txt
scrutinydebugger-0.9.2.dist-info/top_level.txt
scrutinydebugger-0.9.2.dist-info/RECORD
