Metadata-Version: 2.4
Name: scrutinydebugger
Version: 0.9.2
Summary: Scrutiny Debugger Python framework
Home-page: https://github.com/scrutinydebugger/scrutiny-main
Author: Scrutiny Debugger
License: MIT
Requires-Python: >=3.10
License-File: LICENSE
Requires-Dist: appdirs==1.4.4
Requires-Dist: pyelftools==0.32
Requires-Dist: sortedcontainers==2.4.0
Requires-Dist: pyserial==3.5
Requires-Dist: pylink-square==1.3.0
Requires-Dist: PySide6-QtAds==4.4.0
Requires-Dist: PySide6==6.9.0
Requires-Dist: python-can==4.5.0
Requires-Dist: typing-extensions==4.12.2
Provides-Extra: test
Requires-Dist: mypy; extra == "test"
Requires-Dist: coverage; extra == "test"
Requires-Dist: sphinx-book-theme==1.1.2; extra == "test"
Requires-Dist: sphinx==7.2.6; extra == "test"
Provides-Extra: dev
Requires-Dist: mypy; extra == "dev"
Requires-Dist: ipdb; extra == "dev"
Requires-Dist: autopep8; extra == "dev"
Requires-Dist: coverage; extra == "dev"
Requires-Dist: sphinx-book-theme==1.1.2; extra == "dev"
Requires-Dist: sphinx==7.2.6; extra == "dev"
Provides-Extra: build
Requires-Dist: nuitka==2.6.9; extra == "build"
Requires-Dist: imageio==2.37.0; extra == "build"
Requires-Dist: build==1.2.2; extra == "build"
Requires-Dist: pip-licenses==5.0.0; extra == "build"
Dynamic: author
Dynamic: home-page
Dynamic: license
Dynamic: license-file
Dynamic: provides-extra
Dynamic: requires-dist
Dynamic: requires-python
Dynamic: summary
